LICENSE.md
ml_logger/__init__.py
ml_logger/caches/__init__.py
ml_logger/caches/key_value_cache.py
ml_logger/caches/summary_cache.py
ml_logger/cli/download.py
ml_logger/cli/upload.py
ml_logger/full_duplex.py
ml_logger/helpers/__init__.py
ml_logger/helpers/color_helpers.py
ml_logger/helpers/data_helpers.py
ml_logger/helpers/default_set.py
ml_logger/helpers/file_helpers.py
ml_logger/helpers/func_helpers.py
ml_logger/helpers/print_utils.py
ml_logger/job.py
ml_logger/log_client.py
ml_logger/ml_logger.py
ml_logger/nb.py
ml_logger/requests.py
ml_logger/serdes.py
ml_logger/server.py
ml_logger/structs.py
ml_logger/wrappers/__init__.py
ml_logger/wrappers/analysis_wrapper.py
ml_logger-0.10.36.dist-info/LICENSE.md
ml_logger-0.10.36.dist-info/WHEEL
ml_logger-0.10.36.dist-info/entry_points.txt
ml_logger-0.10.36.dist-info/METADATA
ml_logger-0.10.36.dist-info/RECORD
