Metadata-Version: 2.1
Name: ml-logger
Version: 0.10.36
Summary: 
Home-page: https://github.com/geyang/ml-logger
License: MIT
Keywords: ml_logger,visualization,logging,debug,debugging
Author: Ge Yang
Author-email: geyang@mit.edu
Requires-Python: >=3.8.0
Classifier: Development Status :: 4 - Beta
Classifier: Intended Audience :: Science/Research
Classifier: License :: OSI Approved :: MIT License
Classifier: Programming Language :: Python :: 3
Classifier: Programming Language :: Python :: 3.8
Classifier: Programming Language :: Python :: 3.9
Classifier: Programming Language :: Python :: 3.10
Classifier: Programming Language :: Python :: 3.11
Classifier: Programming Language :: Python :: 3
Requires-Dist: boto3
Requires-Dist: cloudpickle (==3.1.1)
Requires-Dist: dill
Requires-Dist: expandvars
Requires-Dist: google-api-python-client
Requires-Dist: google-cloud-storage
Requires-Dist: imageio
Requires-Dist: imageio-ffmpeg
Requires-Dist: jaynes (>=0.9.0)
Requires-Dist: matplotlib
Requires-Dist: more-itertools
Requires-Dist: numpy
Requires-Dist: params-proto (>=2.10.0)
Requires-Dist: pillow
Requires-Dist: pycurl
Requires-Dist: requests
Requires-Dist: requests-futures
Requires-Dist: requests-toolbelt
Requires-Dist: ruamel.yaml
Requires-Dist: sanic (==20.9.0)
Requires-Dist: sanic-cors (==0.10.0.post3)
Requires-Dist: sanic-routing (==22.3.0)
Requires-Dist: scikit-image
Requires-Dist: scikit-video
Requires-Dist: scipy
Requires-Dist: termcolor
Requires-Dist: urllib3
Requires-Dist: wcmatch
Project-URL: Repository, https://github.com/geyang/ml-logger
